jhstest/__init__.py
jhstest/__jhstest.py
jhstest/jhstest.py
jhstest/ts1/__init__.py
jhstest/ts1/ts1.py
test/__init__.py
test/test.py
jhstest-0.1.5.dist-info/LICENSE
jhstest-0.1.5.dist-info/METADATA
jhstest-0.1.5.dist-info/WHEEL
jhstest-0.1.5.dist-info/top_level.txt
jhstest-0.1.5.dist-info/RECORD
