Metadata-Version: 2.1
Name: jhstest
Version: 0.1.5
Summary: A small example package
Home-page: https://github.com/pypa/sampleproject
Author: hyeonsangjeon
Author-email: wingnut0310@gmail.com
License: UNKNOWN
Platform: UNKNOWN
Classifier: Programming Language :: Python :: 3.7
Classifier: License :: OSI Approved :: MIT License
Classifier: Operating System :: OS Independent
Requires-Dist: wordcloud
Requires-Dist: matplotlib
Requires-Dist: seaborn
Requires-Dist: plotly
